phoonnx/__init__.py
phoonnx/cli.py
phoonnx/config.py
phoonnx/model_manager.py
phoonnx/opm.py
phoonnx/phoneme_ids.py
phoonnx/util.py
phoonnx/version.py
phoonnx/voice.py
phoonnx/locale/ca/phonetic_spellings.txt
phoonnx/locale/en/phonetic_spellings.txt
phoonnx/locale/gl/phonetic_spellings.txt
phoonnx/locale/pt/phonetic_spellings.txt
phoonnx/phonemizers/__init__.py
phoonnx/phonemizers/ar.py
phoonnx/phonemizers/base.py
phoonnx/phonemizers/en.py
phoonnx/phonemizers/fa.py
phoonnx/phonemizers/gl.py
phoonnx/phonemizers/he.py
phoonnx/phonemizers/ja.py
phoonnx/phonemizers/ko.py
phoonnx/phonemizers/mul.py
phoonnx/phonemizers/mwl.py
phoonnx/phonemizers/pt.py
phoonnx/phonemizers/vi.py
phoonnx/phonemizers/zh.py
phoonnx/thirdparty/__init__.py
phoonnx/thirdparty/arpa2ipa.py
phoonnx/thirdparty/bw2ipa.py
phoonnx/thirdparty/hangul2ipa.py
phoonnx/thirdparty/zh_num.py
phoonnx/thirdparty/cotovia/cotovia_aarch64
phoonnx/thirdparty/cotovia/cotovia_x86_64
phoonnx/thirdparty/ko_tables/aspiration.csv
phoonnx/thirdparty/ko_tables/assimilation.csv
phoonnx/thirdparty/ko_tables/double_coda.csv
phoonnx/thirdparty/ko_tables/hanja.tsv
phoonnx/thirdparty/ko_tables/ipa.csv
phoonnx/thirdparty/ko_tables/neutralization.csv
phoonnx/thirdparty/ko_tables/tensification.csv
phoonnx/thirdparty/ko_tables/yale.csv
phoonnx/thirdparty/kog2p/__init__.py
phoonnx/thirdparty/kog2p/rulebook.txt
phoonnx/thirdparty/mantoq/__init__.py
phoonnx/thirdparty/mantoq/num2words.py
phoonnx/thirdparty/mantoq/unicode_symbol2label.py
phoonnx/thirdparty/mantoq/buck/__init__.py
phoonnx/thirdparty/mantoq/buck/phonetise_buckwalter.py
phoonnx/thirdparty/mantoq/buck/symbols.py
phoonnx/thirdparty/mantoq/buck/tokenization.py
phoonnx/thirdparty/mantoq/pyarabic/__init__.py
phoonnx/thirdparty/mantoq/pyarabic/arabrepr.py
phoonnx/thirdparty/mantoq/pyarabic/araby.py
phoonnx/thirdparty/mantoq/pyarabic/named_const.py
phoonnx/thirdparty/mantoq/pyarabic/normalize.py
phoonnx/thirdparty/mantoq/pyarabic/number.py
phoonnx-0.5.4.dist-info/METADATA
phoonnx-0.5.4.dist-info/WHEEL
phoonnx-0.5.4.dist-info/entry_points.txt
phoonnx-0.5.4.dist-info/top_level.txt
phoonnx-0.5.4.dist-info/RECORD
