Metadata-Version: 2.4
Name: phoonnx
Version: 0.5.4
Home-page: https://github.com/TigreGotico/phoonnx
Author: JarbasAi
Author-email: jarbasai@mailfence.com
Requires-Dist: numpy
Requires-Dist: onnxruntime
Requires-Dist: quebra-frases
Requires-Dist: langcodes
Requires-Dist: ovos-number-parser>=0.4.0
Requires-Dist: ovos-date-parser>=0.6.4a1
Provides-Extra: cs
Requires-Dist: gruut[cs]<3.0,>=2.3.0; extra == "cs"
Requires-Dist: epitran; extra == "cs"
Provides-Extra: mr
Requires-Dist: epitran; extra == "mr"
Provides-Extra: tpi
Requires-Dist: epitran; extra == "tpi"
Provides-Extra: so
Requires-Dist: epitran; extra == "so"
Provides-Extra: uz
Requires-Dist: epitran; extra == "uz"
Provides-Extra: de
Requires-Dist: gruut[de]<3.0,>=2.3.0; extra == "de"
Requires-Dist: epitran; extra == "de"
Provides-Extra: th
Requires-Dist: epitran; extra == "th"
Provides-Extra: ka
Requires-Dist: epitran; extra == "ka"
Provides-Extra: uk
Requires-Dist: epitran; extra == "uk"
Provides-Extra: en
Requires-Dist: epitran; extra == "en"
Requires-Dist: gruut[en]<3.0,>=2.3.0; extra == "en"
Requires-Dist: misaki[en]; extra == "en"
Provides-Extra: uew
Requires-Dist: epitran; extra == "uew"
Provides-Extra: kbd
Requires-Dist: epitran; extra == "kbd"
Provides-Extra: hr
Requires-Dist: epitran; extra == "hr"
Provides-Extra: sv
Requires-Dist: gruut[sv]<3.0,>=2.3.0; extra == "sv"
Requires-Dist: epitran; extra == "sv"
Provides-Extra: ko
Requires-Dist: g2pk; extra == "ko"
Requires-Dist: epitran; extra == "ko"
Requires-Dist: misaki[ko]; extra == "ko"
Provides-Extra: got
Requires-Dist: epitran; extra == "got"
Provides-Extra: id
Requires-Dist: epitran; extra == "id"
Provides-Extra: sn
Requires-Dist: epitran; extra == "sn"
Provides-Extra: ug
Requires-Dist: epitran; extra == "ug"
Provides-Extra: az
Requires-Dist: epitran; extra == "az"
Provides-Extra: mt
Requires-Dist: epitran; extra == "mt"
Provides-Extra: pl
Requires-Dist: epitran; extra == "pl"
Provides-Extra: ceb
Requires-Dist: epitran; extra == "ceb"
Provides-Extra: ky
Requires-Dist: epitran; extra == "ky"
Provides-Extra: sq
Requires-Dist: epitran; extra == "sq"
Provides-Extra: ny
Requires-Dist: epitran; extra == "ny"
Provides-Extra: ti
Requires-Dist: epitran; extra == "ti"
Provides-Extra: sg
Requires-Dist: epitran; extra == "sg"
Provides-Extra: et
Requires-Dist: epitran; extra == "et"
Provides-Extra: eo
Requires-Dist: epitran; extra == "eo"
Provides-Extra: tk
Requires-Dist: epitran; extra == "tk"
Provides-Extra: yue
Requires-Dist: epitran; extra == "yue"
Provides-Extra: luy
Requires-Dist: epitran; extra == "luy"
Provides-Extra: jam
Requires-Dist: epitran; extra == "jam"
Provides-Extra: hsn
Requires-Dist: epitran; extra == "hsn"
Provides-Extra: fil
Requires-Dist: epitran; extra == "fil"
Provides-Extra: ml
Requires-Dist: epitran; extra == "ml"
Provides-Extra: mwl
Requires-Dist: mwl_phonemizer; extra == "mwl"
Provides-Extra: lez
Requires-Dist: epitran; extra == "lez"
Provides-Extra: si
Requires-Dist: epitran; extra == "si"
Provides-Extra: kk
Requires-Dist: epitran; extra == "kk"
Provides-Extra: hi
Requires-Dist: epitran; extra == "hi"
Provides-Extra: quy
Requires-Dist: epitran; extra == "quy"
Provides-Extra: zh
Requires-Dist: g2pM; extra == "zh"
Requires-Dist: misaki[zh]; extra == "zh"
Requires-Dist: epitran; extra == "zh"
Requires-Dist: pypinyin; extra == "zh"
Requires-Dist: xpinyin; extra == "zh"
Requires-Dist: pinyin_to_ipa; extra == "zh"
Requires-Dist: jieba; extra == "zh"
Requires-Dist: cn2an; extra == "zh"
Provides-Extra: ru
Requires-Dist: gruut[ru]<3.0,>=2.3.0; extra == "ru"
Requires-Dist: epitran; extra == "ru"
Provides-Extra: aii
Requires-Dist: epitran; extra == "aii"
Provides-Extra: train
Requires-Dist: cython<1,>=0.29.0; extra == "train"
Requires-Dist: librosa<1,>=0.9.2; extra == "train"
Requires-Dist: numpy<2,>=1.19.0; extra == "train"
Requires-Dist: pytorch-lightning<2.0; extra == "train"
Requires-Dist: torch<2,>=1.11.0; extra == "train"
Requires-Dist: click; extra == "train"
Provides-Extra: my
Requires-Dist: epitran; extra == "my"
Provides-Extra: yo
Requires-Dist: epitran; extra == "yo"
Provides-Extra: cjy
Requires-Dist: epitran; extra == "cjy"
Provides-Extra: es
Requires-Dist: gruut[es]<3.0,>=2.3.0; extra == "es"
Requires-Dist: epitran; extra == "es"
Provides-Extra: he
Requires-Dist: phonikud_onnx; extra == "he"
Requires-Dist: phonikud; extra == "he"
Provides-Extra: sr
Requires-Dist: epitran; extra == "sr"
Provides-Extra: fr
Requires-Dist: gruut[fr]<3.0,>=2.3.0; extra == "fr"
Requires-Dist: epitran; extra == "fr"
Provides-Extra: ro
Requires-Dist: epitran; extra == "ro"
Provides-Extra: hmn
Requires-Dist: epitran; extra == "hmn"
Provides-Extra: lt
Requires-Dist: epitran; extra == "lt"
Provides-Extra: ckb
Requires-Dist: epitran; extra == "ckb"
Provides-Extra: tg
Requires-Dist: epitran; extra == "tg"
Provides-Extra: vi
Requires-Dist: misaki[vi]; extra == "vi"
Requires-Dist: epitran; extra == "vi"
Requires-Dist: viphoneme; extra == "vi"
Requires-Dist: underthesea; extra == "vi"
Requires-Dist: eng_to_ipa; extra == "vi"
Requires-Dist: vinorm; extra == "vi"
Provides-Extra: hu
Requires-Dist: epitran; extra == "hu"
Provides-Extra: pt
Requires-Dist: gruut[pt]<3.0,>=2.3.0; extra == "pt"
Requires-Dist: epitran; extra == "pt"
Requires-Dist: tugaphone; extra == "pt"
Provides-Extra: ms
Requires-Dist: epitran; extra == "ms"
Provides-Extra: mi
Requires-Dist: epitran; extra == "mi"
Provides-Extra: pa
Requires-Dist: epitran; extra == "pa"
Provides-Extra: za
Requires-Dist: epitran; extra == "za"
Provides-Extra: lv
Requires-Dist: epitran; extra == "lv"
Provides-Extra: am
Requires-Dist: epitran; extra == "am"
Provides-Extra: ca
Requires-Dist: gruut[ca]<3.0,>=2.3.0; extra == "ca"
Requires-Dist: epitran; extra == "ca"
Provides-Extra: om
Requires-Dist: epitran; extra == "om"
Provides-Extra: rw
Requires-Dist: epitran; extra == "rw"
Provides-Extra: nl
Requires-Dist: gruut[nl]<3.0,>=2.3.0; extra == "nl"
Provides-Extra: lsm
Requires-Dist: epitran; extra == "lsm"
Provides-Extra: bn
Requires-Dist: epitran; extra == "bn"
Provides-Extra: fa
Requires-Dist: persian_phonemizer; extra == "fa"
Requires-Dist: gruut[fa]<3.0,>=2.3.0; extra == "fa"
Requires-Dist: epitran; extra == "fa"
Provides-Extra: eu
Requires-Dist: epitran; extra == "eu"
Provides-Extra: te
Requires-Dist: epitran; extra == "te"
Provides-Extra: km
Requires-Dist: epitran; extra == "km"
Provides-Extra: lij
Requires-Dist: epitran; extra == "lij"
Provides-Extra: tr
Requires-Dist: epitran; extra == "tr"
Provides-Extra: ku
Requires-Dist: epitran; extra == "ku"
Provides-Extra: lb
Requires-Dist: gruut[lb]<3.0,>=2.3.0; extra == "lb"
Provides-Extra: ta
Requires-Dist: epitran; extra == "ta"
Provides-Extra: av
Requires-Dist: epitran; extra == "av"
Provides-Extra: ha
Requires-Dist: epitran; extra == "ha"
Provides-Extra: ff
Requires-Dist: epitran; extra == "ff"
Provides-Extra: fi
Requires-Dist: epitran; extra == "fi"
Provides-Extra: sw
Requires-Dist: gruut[sw]<3.0,>=2.3.0; extra == "sw"
Requires-Dist: epitran; extra == "sw"
Provides-Extra: ilo
Requires-Dist: epitran; extra == "ilo"
Provides-Extra: ja
Requires-Dist: pyopenjtalk; extra == "ja"
Requires-Dist: pykakasi; extra == "ja"
Requires-Dist: cutlet; extra == "ja"
Requires-Dist: unidic-lite; extra == "ja"
Requires-Dist: misaki[ja]; extra == "ja"
Provides-Extra: ar
Requires-Dist: gruut[ar]<3.0,>=2.3.0; extra == "ar"
Requires-Dist: epitran; extra == "ar"
Provides-Extra: zu
Requires-Dist: epitran; extra == "zu"
Provides-Extra: xh
Requires-Dist: epitran; extra == "xh"
Provides-Extra: lo
Requires-Dist: epitran; extra == "lo"
Provides-Extra: gl
Requires-Dist: epitran; extra == "gl"
Provides-Extra: aa
Requires-Dist: epitran; extra == "aa"
Provides-Extra: it
Requires-Dist: gruut[it]<3.0,>=2.3.0; extra == "it"
Requires-Dist: epitran; extra == "it"
Provides-Extra: ur
Requires-Dist: epitran; extra == "ur"
Provides-Extra: hak
Requires-Dist: epitran; extra == "hak"
Provides-Extra: wuu
Requires-Dist: epitran; extra == "wuu"
Provides-Extra: csb
Requires-Dist: epitran; extra == "csb"
Provides-Extra: nan
Requires-Dist: epitran; extra == "nan"
Provides-Extra: jv
Requires-Dist: epitran; extra == "jv"
Provides-Extra: or
Requires-Dist: epitran; extra == "or"
Provides-Extra: gan
Requires-Dist: epitran; extra == "gan"
Provides-Extra: rn
Requires-Dist: epitran; extra == "rn"
Dynamic: author
Dynamic: author-email
Dynamic: home-page
Dynamic: provides-extra
Dynamic: requires-dist
